pydm_alarm_plugin/README.md
pydm_alarm_plugin/__init__.py
pydm_alarm_plugin/alarm_plugin.py
slam/__init__.py
slam/_version.py
slam/alarm_configuration_widget.py
slam/alarm_item.py
slam/alarm_table_model.py
slam/alarm_table_view.py
slam/alarm_tree_model.py
slam/alarm_tree_view.py
slam/archive_search.py
slam/kafka_reader.py
slam/main_window.py
slam/permissions.py
slam/tests/__init__.py
slam/tests/conftest.py
slam/tests/test_alarm_configuration_widget.py
slam/tests/test_alarm_item.py
slam/tests/test_alarm_plugin.py
slam/tests/test_alarm_table_model.py
slam/tests/test_alarm_table_view.py
slam/tests/test_alarm_tree_model.py
slam/tests/test_alarm_tree_view.py
slam/tests/test_archive_search.py
slam/tests/test_main_window.py
slam/tests/test_permissions.py
slam_launcher/__init__.py
slam_launcher/main.py
slac_alarm_manager-1.4.0.dist-info/LICENSE.md
slac_alarm_manager-1.4.0.dist-info/METADATA
slac_alarm_manager-1.4.0.dist-info/WHEEL
slac_alarm_manager-1.4.0.dist-info/entry_points.txt
slac_alarm_manager-1.4.0.dist-info/top_level.txt
slac_alarm_manager-1.4.0.dist-info/RECORD
