Metadata-Version: 2.2
Name: slac-alarm-manager
Version: 1.4.0
Summary: Python interface for managing alarms
Author: SLAC National Accelerator Laboratory
License: Copyright (c) 2017 – 2024, The Board of Trustees of the Leland Stanford Junior University, through SLAC National Accelerator Laboratory (subject to receipt of any required approvals from the U.S. Dept. of Energy). All rights reserved. Redistribution and use in source and binary forms, with or without modification, are permitted provided that the following conditions are met:
Project-URL: Homepage, https://github.com/slaclab/slac-alarm-manager
Project-URL: Documentation, https://slaclab.github.io/slac-alarm-manager/
Classifier: Development Status :: 5 - Production/Stable
Classifier: Natural Language :: English
Classifier: Programming Language :: Python :: 3
Requires-Python: >=3.9
License-File: LICENSE.md
Requires-Dist: kafka-python
Requires-Dist: pydm
Requires-Dist: PyQt5
Requires-Dist: qtpy
Provides-Extra: dev
Requires-Dist: pytest; extra == "dev"
Requires-Dist: pytest-qt; extra == "dev"
Requires-Dist: pytest-cov; extra == "dev"
Requires-Dist: pre-commit; extra == "dev"
Provides-Extra: docs
Requires-Dist: mkdocs; extra == "docs"
Requires-Dist: mkdocs-material; extra == "docs"
